arfindata/ARdata.py
arfindata/__init__.py
arfindata/sh.py
arfindata/sz.py
arfindata-0.1.4.dist-info/LICENSE.txt
arfindata-0.1.4.dist-info/METADATA
arfindata-0.1.4.dist-info/WHEEL
arfindata-0.1.4.dist-info/top_level.txt
arfindata-0.1.4.dist-info/RECORD
